calculator/__init__.py
calculator/test__init__.py
not_so_basic_calculator-0.1.1.dist-info/LICENSE
not_so_basic_calculator-0.1.1.dist-info/WHEEL
not_so_basic_calculator-0.1.1.dist-info/METADATA
not_so_basic_calculator-0.1.1.dist-info/RECORD
