Metadata-Version: 2.1
Name: not-so-basic-calculator
Version: 0.1.1
Summary: A module for basic calculator class.
Author-email: Adomas Vysniauskas <adomasofm@gmail.com>
Classifier: License :: OSI Approved :: MIT License
Requires-Dist: pytest ; extra == "test"
Requires-Dist: mypy ; extra == "test"
Requires-Dist: flake8 ; extra == "test"
Project-URL: Documentation, https://github.com/punkuotukas/TC_1.1.5_calculator#readme
Project-URL: Source, https://github.com/punkuotukas/TC_1.1.5_calculator
Provides-Extra: test
